voxel/__init__.py
voxel/acquisition.py
voxel/affine.py
voxel/bounds.py
voxel/caching.py
voxel/filters.py
voxel/mesh.py
voxel/slicing.py
voxel/space.py
voxel/volume.py
voxel/io/__init__.py
voxel/io/affine.py
voxel/io/mesh.py
voxel/io/utility.py
voxel/io/volume.py
voxel-0.1.1.dist-info/METADATA
voxel-0.1.1.dist-info/WHEEL
voxel-0.1.1.dist-info/top_level.txt
voxel-0.1.1.dist-info/RECORD
