Metadata-Version: 2.4
Name: voxel
Version: 0.1.1
Summary: Torch framework for volumetric medical imaging structures
Author: Andrew Hoopes
Keywords: medical imaging,deep-learning,AI,MRI
Classifier: Topic :: Scientific/Engineering
Classifier: Intended Audience :: Science/Research
Classifier: Programming Language :: Python :: 3
Classifier: License :: OSI Approved :: MIT License
Classifier: Operating System :: OS Independent
Requires-Python: >=3.8
Requires-Dist: numpy
Requires-Dist: torch>=1.12
